corals/__init__.py
corals/threads.py
corals/_experimental/test_correlation_topk.py
corals/_experimental/test_joblib_context_size_large.py
corals/_experimental/test_joblib_context_size_large_small.py
corals/_experimental/test_presorting.py
corals/_experimental/test_topk_reduce.py
corals/correlation/utils.py
corals/correlation/utils_numba.py
corals/correlation/full/base.py
corals/correlation/full/baselines.py
corals/correlation/full/default.py
corals/correlation/full/matmul.py
corals/correlation/full/_deprecated/original.py
corals/correlation/threshold/base.py
corals/correlation/threshold/loop.py
corals/correlation/threshold/_deprecated/original.py
corals/correlation/topk/base.py
corals/correlation/topk/baselines.py
corals/correlation/topk/default.py
corals/correlation/topk/helper.py
corals/correlation/topk/_deprecated/batched_generic.py
corals/correlation/topk/_deprecated/batched_joblib.py
corals/correlation/topk/_deprecated/batched_loop.py
corals/correlation/topk/_deprecated/batched_memmap.py
corals/correlation/topk/_deprecated/batched_old.py
corals/correlation/topk/_deprecated/nmslib.py
corals/correlation/topk/_deprecated/original.py
corals/correlation/topk/_experimental/distributed.py
corals/correlation/topk/_experimental/nndescent.py
corals/correlation/topk/batched/base.py
corals/correlation/topk/batched/matmul.py
corals/correlation/topk/batched/nearest_neighbors.py
corals/correlation/topk/batched/nearest_neighbors_ann_ngt.py
corals/correlation/topk/batched/nearest_neighbors_ann_nmslib.py
corals/correlation/topk/batched/nearest_neighbors_balltree.py
corals/correlation/topk/batched/reduce.py
corals/correlation/topk/batched/result_handler.py
corals/correlation/topkdiff/base.py
corals/correlation/topkdiff/default.py
corals/correlation/topkdiff/original.py
corals/sorting/parallel.py
corals-0.1.7.dist-info/METADATA
corals-0.1.7.dist-info/WHEEL
corals-0.1.7.dist-info/top_level.txt
corals-0.1.7.dist-info/RECORD
