Metadata-Version: 2.1
Name: corals
Version: 0.1.7
Summary: CorALS is an open-source software package for the construction and analysis of large-scale correlation networks for high-dimensional data.
Home-page: https://github.com/mgbckr/corals-python
Author: Martin Becker
Author-email: mgbckr@stanford.edu
License: MIT
Project-URL: Documentation, https://github.com/mgbckr/corals-python
Project-URL: Source, https://github.com/mgbckr/corals-python
Project-URL: Tracker, https://github.com/mgbckr/corals-python/issues
Project-URL: Download, https://pypi.org/project/corals/#files
Platform: any
Classifier: Development Status :: 4 - Beta
Classifier: Programming Language :: Python
Requires-Python: >=3.9
Requires-Dist: numba >=0.52.0
Requires-Dist: numpy <2.0.0,>=1.20.3
Requires-Dist: joblib <2.0.0,>=1.0.0
Requires-Dist: scipy <2.0.0,>=1.6.3
Requires-Dist: scikit-learn <2.0.0,>=0.24.2
Requires-Dist: importlib-metadata ; python_version < "3.8"
Provides-Extra: testing
Requires-Dist: setuptools ; extra == 'testing'
Requires-Dist: pytest ; extra == 'testing'
Requires-Dist: pytest-cov ; extra == 'testing'
Requires-Dist: nbmake ; extra == 'testing'
Requires-Dist: statsmodels ; extra == 'testing'
